customLoggerZhatlebaye/__init__.py
customLoggerZhatlebaye/logger.py
custom_logger_zhatlebaye-0.1.0.dist-info/METADATA
custom_logger_zhatlebaye-0.1.0.dist-info/WHEEL
custom_logger_zhatlebaye-0.1.0.dist-info/top_level.txt
custom_logger_zhatlebaye-0.1.0.dist-info/RECORD
