Metadata-Version: 2.1
Name: custom-logger-zhatlebaye
Version: 0.1.0
Summary: Custom logger
Author: Adil, Bauka, Yerlan, Dimashka
